reposmgr.py
reposmgr-0.0.5.data/scripts/reposmgr-ensure-all
reposmgr-0.0.5.data/scripts/reposmgr-ensure-repo
reposmgr-0.0.5.data/scripts/reposmgr-reclone-all
reposmgr-0.0.5.data/scripts/reposmgr-reclone-repo
reposmgr-0.0.5.data/scripts/reposmgr-status
reposmgr-0.0.5.data/scripts/reposmgr-switch-version
reposmgr-0.0.5.data/scripts/reposmgr-update-all
reposmgr-0.0.5.data/scripts/reposmgr-update-repo
reposmgr-0.0.5.dist-info/DESCRIPTION.rst
reposmgr-0.0.5.dist-info/METADATA
reposmgr-0.0.5.dist-info/RECORD
reposmgr-0.0.5.dist-info/WHEEL
reposmgr-0.0.5.dist-info/entry_points.txt
reposmgr-0.0.5.dist-info/metadata.json
reposmgr-0.0.5.dist-info/top_level.txt
