Metadata-Version: 2.0
Name: reposmgr
Version: 0.0.5
Summary: (Very) Simple set of commands to manage a set of repository with one file (git only)
Home-page: https://bitbucket.org/jqb/reposmgr
Author: Jakub Janoszek
Author-email: jqbj@protonmail.com
License: UNKNOWN
Platform: UNKNOWN
